shuttl/core/__init__.py
shuttl/core/py.typed
shuttl/core/_jsii/__init__.py
shuttl/core/_jsii/core@0.4.9.jsii.tgz
shuttl_core-0.4.9.dist-info/LICENSE
shuttl_core-0.4.9.dist-info/METADATA
shuttl_core-0.4.9.dist-info/WHEEL
shuttl_core-0.4.9.dist-info/top_level.txt
shuttl_core-0.4.9.dist-info/RECORD
